Metadata-Version: 1.0
Name: bodhion
Version: 1.0.0
Summary: Crypto trading bot
Home-page: https://github.com/bodhion/bodhion
Author: bodhion
Author-email: bodhion@bodhion.com
License: MIT
Platform: UNKNOWN
